{"nodes": [{"id": "paperscan_core_di_dicontainer_swift", "label": "DIContainer.swift", "file_type": "code", "source_file": "paperscan/Core/DI/DIContainer.swift", "source_location": "L1"}, {"id": "dicontainer_dicontainer", "label": "DIContainer", "file_type": "code", "source_file": "paperscan/Core/DI/DIContainer.swift", "source_location": "L4"}, {"id": "dicontainer_dicontainer_init", "label": ".init()", "file_type": "code", "source_file": "paperscan/Core/DI/DIContainer.swift", "source_location": "L25"}], "edges": [{"source": "paperscan_core_di_dicontainer_swift", "target": "foundation", "relation": "imports", "confidence": "EXTRACTED", "source_file": "paperscan/Core/DI/DIContainer.swift", "source_location": "L1", "weight": 1.0}, {"source": "paperscan_core_di_dicontainer_swift", "target": "observation", "relation": "imports", "confidence": "EXTRACTED", "source_file": "paperscan/Core/DI/DIContainer.swift", "source_location": "L2", "weight": 1.0}, {"source": "paperscan_core_di_dicontainer_swift", "target": "dicontainer_dicontainer", "relation": "contains", "confidence": "EXTRACTED", "source_file": "paperscan/Core/DI/DIContainer.swift", "source_location": "L4", "weight": 1.0}, {"source": "dicontainer_dicontainer", "target": "dicontainer_dicontainer_init", "relation": "method", "confidence": "EXTRACTED", "source_file": "paperscan/Core/DI/DIContainer.swift", "source_location": "L25", "weight": 1.0}], "raw_calls": []}